eriparse/__init__.py
eriparse/main.py
eriparse/parse.py
eriparse-0.0.2.dist-info/LICENSE
eriparse-0.0.2.dist-info/METADATA
eriparse-0.0.2.dist-info/WHEEL
eriparse-0.0.2.dist-info/top_level.txt
eriparse-0.0.2.dist-info/RECORD
