Metadata-Version: 2.1
Name: eriparse
Version: 0.0.2
Summary: HTML Parser of Economic Research Institute Cost of Living HTML.
Author: Nicholas Grillini-Lawrence
License: MIT
Keywords: webscraper,webscraping,web-scraper,web-scraping,html,eri,erieri.com,cost-of-living,python
License-File: LICENSE
Requires-Dist: bs4
Provides-Extra: dev
Requires-Dist: black ; extra == 'dev'
Requires-Dist: pre-commit ; extra == 'dev'
Requires-Dist: ruff ; extra == 'dev'
Requires-Dist: mypy ; extra == 'dev'
